digital_twin_distiller/__init__.py
digital_twin_distiller/__main__.py
digital_twin_distiller/boundaries.py
digital_twin_distiller/cli.py
digital_twin_distiller/doe.py
digital_twin_distiller/encapsulator.py
digital_twin_distiller/femm_wrapper.py
digital_twin_distiller/geo_parser.py
digital_twin_distiller/geometry.py
digital_twin_distiller/gmsh.py
digital_twin_distiller/material.py
digital_twin_distiller/metadata.py
digital_twin_distiller/model.py
digital_twin_distiller/modelpaths.py
digital_twin_distiller/modelpiece.py
digital_twin_distiller/objects.py
digital_twin_distiller/platforms/__init__.py
digital_twin_distiller/platforms/agros2d.py
digital_twin_distiller/platforms/femm.py
digital_twin_distiller/platforms/ng_electrostatic.py
digital_twin_distiller/platforms/ng_magnetostatic.py
digital_twin_distiller/platforms/ngsolve.py
digital_twin_distiller/platforms/platform.py
digital_twin_distiller/resources/doc_template/docs/images/tutorial.gif
digital_twin_distiller/resources/doc_template/docs/index.md
digital_twin_distiller/resources/doc_template/mkdocs.yml
digital_twin_distiller/resources/model_template/model.py
digital_twin_distiller/resources/model_template/simulation.py
digital_twin_distiller/simulationproject.py
digital_twin_distiller/snapshot.py
digital_twin_distiller/utils.py
digital_twin_distiller-2022.3.dist-info/entry_points.txt
digital_twin_distiller-2022.3.dist-info/LICENSE
digital_twin_distiller-2022.3.dist-info/WHEEL
digital_twin_distiller-2022.3.dist-info/METADATA
digital_twin_distiller-2022.3.dist-info/RECORD
