Metadata-Version: 2.1
Name: digital-twin-distiller
Version: 2022.3
Summary: Python project for creating a long-lasting, encapsulated version of your numerical simulation or your machine-learning-based project.
License: AGPL
Author: MONTANA Knowledge Management ltd.
Author-email: info@distiller.dev
Requires-Python: >=3.8,<3.10
Classifier: License :: Other/Proprietary License
Classifier: Programming Language :: Python :: 3
Classifier: Programming Language :: Python :: 3.8
Classifier: Programming Language :: Python :: 3.9
Requires-Dist: Jinja2 (>3.0.1)
Requires-Dist: Shapely (>1.8.0)
Requires-Dist: aiofiles (>0.7.0)
Requires-Dist: ezdxf (>0.16.5)
Requires-Dist: fastapi (>0.70.0)
Requires-Dist: gmsh (>4.8.4)
Requires-Dist: importlib-resources (>5.4.0)
Requires-Dist: matplotlib (>3.5.1)
Requires-Dist: mkdocs (>1.2.3)
Requires-Dist: mkdocs-git-revision-date-plugin (>0.3.1)
Requires-Dist: mkdocs-material (>7.3.6)
Requires-Dist: mkdocstrings[python] (>0.16.2)
Requires-Dist: networkx (>2.6.3)
Requires-Dist: numpy (>1.21.0)
Requires-Dist: pydantic (>1.8.2)
Requires-Dist: pygmsh (>7.1.13)
Requires-Dist: python-markdown-math (>=0.8,<0.9)
Requires-Dist: requests (>=2.27.1)
Requires-Dist: scipy (>1.7.0)
Requires-Dist: setuptools (>61.2.0)
Requires-Dist: svgpathtools (>1.4.2)
Requires-Dist: uvicorn (>0.15.0)
